pybugmate/__init__.py
pybugmate/autowrap.py
pybugmate/color.py
pybugmate/decorators.py
pybugmate/logger.py
pybugmate/postmortem.py
pybugmate/profiler.py
pybugmate/trace.py
pybugmate/utils.py
pybugmate-0.1.2.dist-info/METADATA
pybugmate-0.1.2.dist-info/WHEEL
pybugmate-0.1.2.dist-info/top_level.txt
pybugmate-0.1.2.dist-info/RECORD
