Metadata-Version: 2.4
Name: pybugmate
Version: 0.1.2
Summary: Effortless debugging, error hints, profiling, and postmortem REPL for Python
Home-page: https://github.com/ANU-2524/pybugmate
Author: ANU SONI
Author-email: anusoni25.2006@gmail.com
Requires-Python: >=3.6
Requires-Dist: IPython
Dynamic: author
Dynamic: author-email
Dynamic: description
Dynamic: description-content-type
Dynamic: home-page
Dynamic: requires-dist
Dynamic: requires-python
Dynamic: summary
